[
    {
        "source": [
            136.4509,
            35.203
        ],
        "target": [
            136.963163,
            35.635566
        ]
    },
    {
        "source": [
            136.513473,
            35.1938815
        ],
        "target": [
            136.6148491,
            35.0836162
        ]
    },
    {
        "source": [
            136.963163,
            35.635566
        ],
        "target": [
            137.298391,
            35.2114317
        ]
    },
    {
        "source": [
            136.9362359,
            35.5280336
        ],
        "target": [
            137.2621732,
            35.1055855
        ]
    },
    {
        "source": [
            137.2621732,
            35.1055855
        ],
        "target": [
            136.99372,
            35.265315
        ]
    },
    {
        "source": [
            137.729048,
            35.162284
        ],
        "target": [
            137.9967366,
            35.709363
        ]
    },
    {
        "source": [
            137.1159646,
            35.1440303
        ],
        "target": [
            136.971497,
            34.960985
        ]
    },
    {
        "source": [
            136.9007535,
            35.0490287
        ],
        "target": [
            136.864044,
            35.006504
        ]
    },
    {
        "source": [
            137.7991592,
            35.0822446
        ],
        "target": [
            138.109435,
            35.0922964
        ]
    },
    {
        "source": [
            137.4704073,
            34.8444319
        ],
        "target": [
            137.7000236,
            34.8049055
        ]
    },
    {
        "source": [
            137.277722,
            34.962503
        ],
        "target": [
            137.1869866,
            34.8709029
        ]
    },
    {
        "source": [
            137.1869866,
            34.8709029
        ],
        "target": [
            136.9621924,
            34.8352672
        ]
    },
    {
        "source": [
            138.6923649,
            35.1750832
        ],
        "target": [
            138.962685,
            35.372763
        ]
    },
    {
        "source": [
            133.405513,
            35.297397
        ],
        "target": [
            131.978929,
            34.696398
        ]
    },
    {
        "source": [
            132.535446,
            34.388148
        ],
        "target": [
            132.25697,
            34.412752
        ]
    },
    {
        "source": [
            133.386658,
            34.803877
        ],
        "target": [
            133.405513,
            35.297397
        ]
    },
    {
        "source": [
            133.386658,
            34.803877
        ],
        "target": [
            132.535446,
            34.388148
        ]
    },
    {
        "source": [
            134.023523,
            34.88857
        ],
        "target": [
            133.386658,
            34.803877
        ]
    },
    {
        "source": [
            131.849094,
            34.122218
        ],
        "target": [
            131.825802,
            34.201555
        ]
    },
    {
        "source": [
            132.475416,
            34.398444
        ],
        "target": [
            132.409394,
            34.457896
        ]
    },
    {
        "source": [
            131.397451,
            34.093249
        ],
        "target": [
            132.735922,
            34.819755
        ]
    },
    {
        "source": [
            133.517083,
            34.532374
        ],
        "target": [
            133.483268,
            34.661012
        ]
    },
    {
        "source": [
            133.066254,
            35.46185
        ],
        "target": [
            133.115085,
            35.469894
        ]
    },
    {
        "source": [
            141.451615,
            43.234974
        ],
        "target": [
            141.534937,
            43.119427
        ]
    },
    {
        "source": [
            142.280925,
            43.8149441
        ],
        "target": [
            142.38684,
            43.753872
        ]
    },
    {
        "source": [
            141.573786,
            42.909509
        ],
        "target": [
            141.418075,
            43.022239
        ]
    },
    {
        "source": [
            140.994535,
            42.401675
        ],
        "target": [
            141.03923,
            42.74577
        ]
    },
    {
        "source": [
            141.03923,
            42.74577
        ],
        "target": [
            141.225943,
            43.057812
        ]
    },
    {
        "source": [
            141.891242,
            43.575337
        ],
        "target": [
            142.323644,
            43.806006
        ]
    },
    {
        "source": [
            141.798975,
            42.881694
        ],
        "target": [
            141.573786,
            42.909509
        ]
    },
    {
        "source": [
            141.556037,
            42.634608
        ],
        "target": [
            141.000765,
            42.327191
        ]
    },
    {
        "source": [
            141.780759,
            42.714851
        ],
        "target": [
            141.451615,
            43.234974
        ]
    },
    {
        "source": [
            141.780759,
            42.714851
        ],
        "target": [
            141.798975,
            42.881694
        ]
    },
    {
        "source": [
            141.534937,
            43.119427
        ],
        "target": [
            141.418075,
            43.022239
        ]
    },
    {
        "source": [
            142.904402,
            43.163317
        ],
        "target": [
            141.798975,
            42.881694
        ]
    },
    {
        "source": [
            136.861409,
            36.5600483
        ],
        "target": [
            136.8394971,
            36.9961896
        ]
    },
    {
        "source": [
            136.4153525,
            35.9963234
        ],
        "target": [
            135.9730227,
            35.5567178
        ]
    },
    {
        "source": [
            135.111247,
            34.932125
        ],
        "target": [
            134.4263298,
            34.8610122
        ]
    },
    {
        "source": [
            135.3460102,
            34.9835895
        ],
        "target": [
            135.111247,
            34.932125
        ]
    },
    {
        "source": [
            135.6186518,
            34.9697212
        ],
        "target": [
            135.657388,
            34.860483
        ]
    },
    {
        "source": [
            135.7140954,
            34.7340614
        ],
        "target": [
            135.6186518,
            34.9697212
        ]
    },
    {
        "source": [
            135.7140954,
            34.7340614
        ],
        "target": [
            135.9017279,
            34.448777
        ]
    },
    {
        "source": [
            135.7140954,
            34.7340614
        ],
        "target": [
            135.6485561,
            34.595993
        ]
    },
    {
        "source": [
            135.896357,
            34.86564
        ],
        "target": [
            136.143015,
            35.007215
        ]
    },
    {
        "source": [
            135.484174,
            34.991057
        ],
        "target": [
            135.688476,
            34.902806
        ]
    },
    {
        "source": [
            135.484174,
            34.991057
        ],
        "target": [
            135.472029,
            34.468099
        ]
    },
    {
        "source": [
            134.717503,
            35.127891
        ],
        "target": [
            135.688476,
            34.902806
        ]
    },
    {
        "source": [
            135.266143,
            35.352126
        ],
        "target": [
            134.717503,
            35.127891
        ]
    },
    {
        "source": [
            135.086816,
            34.711026
        ],
        "target": [
            134.856799,
            34.80198
        ]
    },
    {
        "source": [
            135.501577,
            34.5419455
        ],
        "target": [
            135.361281,
            34.379161
        ]
    },
    {
        "source": [
            135.502222,
            34.213889
        ],
        "target": [
            134.6361684,
            33.8286577
        ]
    },
    {
        "source": [
            130.363916,
            33.469787
        ],
        "target": [
            130.805655,
            33.810192
        ]
    },
    {
        "source": [
            130.363916,
            33.469787
        ],
        "target": [
            130.4042671,
            33.5829018
        ]
    },
    {
        "source": [
            130.363916,
            33.469787
        ],
        "target": [
            130.220057,
            33.595917
        ]
    },
    {
        "source": [
            131.015029,
            33.608532
        ],
        "target": [
            130.4042671,
            33.5829018
        ]
    },
    {
        "source": [
            129.929739,
            33.349297
        ],
        "target": [
            130.363916,
            33.469787
        ]
    },
    {
        "source": [
            129.929739,
            33.349297
        ],
        "target": [
            129.978969,
            33.194808
        ]
    },
    {
        "source": [
            130.799176,
            32.613453
        ],
        "target": [
            130.764771938867,
            32.6680007768411
        ]
    },
    {
        "source": [
            130.805655,
            33.810192
        ],
        "target": [
            130.850077,
            33.827504
        ]
    },
    {
        "source": [
            130.805655,
            33.810192
        ],
        "target": [
            130.76202,
            33.835059
        ]
    },
    {
        "source": [
            130.850077,
            33.827504
        ],
        "target": [
            130.971248,
            33.895654
        ]
    },
    {
        "source": [
            131.638028,
            33.228804
        ],
        "target": [
            131.512644,
            33.18873
        ]
    },
    {
        "source": [
            130.4042671,
            33.5829018
        ],
        "target": [
            130.582267,
            33.478846
        ]
    },
    {
        "source": [
            130.582267,
            33.478846
        ],
        "target": [
            130.460644,
            33.622435
        ]
    },
    {
        "source": [
            130.460644,
            33.622435
        ],
        "target": [
            130.411753,
            33.588897
        ]
    },
    {
        "source": [
            130.448728,
            33.210697
        ],
        "target": [
            130.491228,
            33.381163
        ]
    },
    {
        "source": [
            130.491228,
            33.381163
        ],
        "target": [
            130.49741,
            33.322344
        ]
    },
    {
        "source": [
            127.840328,
            26.429331
        ],
        "target": [
            127.825649,
            26.392154
        ]
    },
    {
        "source": [
            127.726862,
            26.265103
        ],
        "target": [
            127.703124,
            26.22956
        ]
    },
    {
        "source": [
            134.6361684,
            33.8286577
        ],
        "target": [
            135.502222,
            34.213889
        ]
    },
    {
        "source": [
            133.953917,
            34.163394
        ],
        "target": [
            133.7623225,
            34.1851948
        ]
    },
    {
        "source": [
            133.953917,
            34.163394
        ],
        "target": [
            134.05429,
            34.339574
        ]
    },
    {
        "source": [
            134.408009,
            34.001327
        ],
        "target": [
            133.953917,
            34.163394
        ]
    },
    {
        "source": [
            134.408009,
            34.001327
        ],
        "target": [
            134.467979,
            34.068835
        ]
    },
    {
        "source": [
            134.6361684,
            33.8286577
        ],
        "target": [
            134.408009,
            34.001327
        ]
    },
    {
        "source": [
            133.16865,
            33.9313756
        ],
        "target": [
            132.7673768,
            33.8942484
        ]
    },
    {
        "source": [
            133.340937,
            33.765705
        ],
        "target": [
            133.39393,
            33.94346
        ]
    },
    {
        "source": [
            133.6877417,
            33.6485794
        ],
        "target": [
            133.8901336,
            34.0325203
        ]
    },
    {
        "source": [
            133.8901336,
            34.0325203
        ],
        "target": [
            133.953917,
            34.163394
        ]
    },
    {
        "source": [
            140.071754,
            40.16203
        ],
        "target": [
            140.783349,
            40.809874
        ]
    },
    {
        "source": [
            140.426689,
            39.168785
        ],
        "target": [
            140.847854,
            38.605392
        ]
    },
    {
        "source": [
            140.136727,
            39.694588
        ],
        "target": [
            140.426689,
            39.168785
        ]
    },
    {
        "source": [
            140.136727,
            39.694588
        ],
        "target": [
            140.971155,
            39.695115
        ]
    },
    {
        "source": [
            140.950525,
            37.535288
        ],
        "target": [
            140.960925,
            37.360687
        ]
    },
    {
        "source": [
            140.950525,
            37.535288
        ],
        "target": [
            140.423258,
            37.676947
        ]
    },
    {
        "source": [
            140.423258,
            37.676947
        ],
        "target": [
            140.426133,
            37.305622
        ]
    },
    {
        "source": [
            141.196706,
            39.075126
        ],
        "target": [
            140.847854,
            38.605392
        ]
    },
    {
        "source": [
            139.15859,
            37.916819
        ],
        "target": [
            140.117236,
            37.859206
        ]
    },
    {
        "source": [
            138.962685,
            35.372763
        ],
        "target": [
            138.6923649,
            35.1750832
        ]
    },
    {
        "source": [
            140.747974,
            36.988932
        ],
        "target": [
            140.723657,
            37.141173
        ]
    },
    {
        "source": [
            140.723657,
            37.141173
        ],
        "target": [
            140.154167,
            36.522071
        ]
    },
    {
        "source": [
            140.518107,
            36.463984
        ],
        "target": [
            140.154167,
            36.522071
        ]
    },
    {
        "source": [
            139.916744,
            36.654718
        ],
        "target": [
            139.303514,
            36.326465
        ]
    },
    {
        "source": [
            140.027056,
            35.3429
        ],
        "target": [
            140.166566,
            35.499195
        ]
    },
    {
        "source": [
            140.166566,
            35.499195
        ],
        "target": [
            140.069919,
            35.782682
        ]
    },
    {
        "source": [
            140.656193,
            35.897095
        ],
        "target": [
            139.910724,
            35.932338
        ]
    },
    {
        "source": [
            139.832374,
            36.106338
        ],
        "target": [
            139.4370292,
            35.9628844
        ]
    },
    {
        "source": [
            139.303514,
            36.326465
        ],
        "target": [
            139.212485,
            36.219659
        ]
    },
    {
        "source": [
            139.303514,
            36.326465
        ],
        "target": [
            139.4370292,
            35.9628844
        ]
    },
    {
        "source": [
            139.212485,
            36.219659
        ],
        "target": [
            138.937484,
            36.031019
        ]
    },
    {
        "source": [
            138.962685,
            35.372763
        ],
        "target": [
            139.36829,
            35.534528
        ]
    },
    {
        "source": [
            138.937484,
            36.031019
        ],
        "target": [
            139.223398,
            35.715099
        ]
    },
    {
        "source": [
            139.603697,
            35.536028
        ],
        "target": [
            139.45661,
            35.604731
        ]
    },
    {
        "source": [
            139.503027,
            35.654156
        ],
        "target": [
            139.701588,
            35.714231
        ]
    },
    {
        "source": [
            139.503027,
            35.654156
        ],
        "target": [
            139.707409,
            35.69793
        ]
    },
    {
        "source": [
            139.500205,
            35.430999
        ],
        "target": [
            139.45661,
            35.604731
        ]
    },
    {
        "source": [
            139.711043,
            35.500843
        ],
        "target": [
            139.500205,
            35.430999
        ]
    },
    {
        "source": [
            139.7555605,
            35.7029293
        ],
        "target": [
            139.707409,
            35.69793
        ]
    },
    {
        "source": [
            139.4370292,
            35.9628844
        ],
        "target": [
            139.690699,
            36.025932
        ]
    },
    {
        "source": [
            139.6252464,
            35.9731494
        ],
        "target": [
            139.615805,
            35.888647
        ]
    },
    {
        "source": [
            139.719132,
            35.729121
        ],
        "target": [
            139.784859,
            35.82871
        ]
    },
    {
        "source": [
            139.9080179,
            35.6656843
        ],
        "target": [
            139.6686775,
            35.6316764
        ]
    },
    {
        "source": [
            139.7909308,
            35.6478587
        ],
        "target": [
            139.784422,
            35.67562
        ]
    }
]